<Properties StartupConfiguration="{2F161492-41F6-49ED-7E1C-AC11E52EA722}|">
  <MonoDevelop.Ide.Workbench ActiveDocument="Assets/ZombieDescriptionPanel.cs">
    <Files>
      <File FileName="Assets/PlayerUnitsContainer.cs" Line="1" Column="1" />
      <File FileName="Assets/_FreedomForZombie/Scripts/PlayerPrefsUtil.cs" Line="1" Column="1" />
      <File FileName="Assets/_FreedomForZombie/Scripts/JsonUtil.cs" />
      <File FileName="Assets/_FreedomForZombie/Scripts/StateMachine/States/AttackState.cs" />
      <File FileName="Assets/FullZombiesContainer.cs" Line="33" Column="39" />
      <File FileName="Assets/LoginScript.cs" Line="30" Column="26" />
      <File FileName="Assets/_FreedomForZombie/Scripts/PlayfabManager.cs" Line="62" Column="99" />
      <File FileName="Assets/ZombieDescriptionPanel.cs" Line="31" Column="57" />
      <File FileName="Assets/UpgradeOrBayBtn.cs" Line="38" Column="61" />
      <File FileName="Assets/_FreedomForZombie/ScriptableObjects/DamageMultiplierSO.cs" Line="9" Column="22" />
      <File FileName="Assets/_FreedomForZombie/ScriptableObjects/AllZombiesSO.cs" Line="4" Column="1" />
      <File FileName="Assets/_FreedomForZombie/ScriptableObjects/ZombieSO.cs" Line="11" Column="35" />
      <File FileName="Assets/_FreedomForZombie/Scripts/ZombieSpawnArea.cs" Line="53" Column="52" />
      <File FileName="Assets/_FreedomForZombie/Scripts/Unit/Zombie.cs" Line="18" Column="50" />
    </Files>
    <Pads>
      <Pad Id="ProjectPad">
        <State name="__root__">
          <Node name="Z Project" expanded="True">
            <Node name="Assets" expanded="True">
              <Node name="_FreedomForZombie" expanded="True">
                <Node name="ScriptableObjects" expanded="True">
                  <Node name="Waves" expanded="True" />
                </Node>
                <Node name="Scripts" expanded="True">
                  <Node name="Map" expanded="True" />
                  <Node name="StateMachine" expanded="True">
                    <Node name="States" expanded="True" />
                    <Node name="Transitions" expanded="True" />
                  </Node>
                  <Node name="Unit" expanded="True" />
                </Node>
              </Node>
              <Node name="ZombieDescriptionPanel.cs" selected="True" />
            </Node>
          </Node>
        </State>
      </Pad>
    </Pads>
  </MonoDevelop.Ide.Workbench>
  <MonoDevelop.Ide.DebuggingService.PinnedWatches />
  <MonoDevelop.Ide.Workspace ActiveConfiguration="Debug" />
  <MonoDevelop.Ide.ItemProperties.Assembly-CSharp PreferredExecutionTarget="44419f87-b524-44c5-9931-394412688feb" />
  <MonoDevelop.Ide.DebuggingService.Breakpoints>
    <BreakpointStore>
      <Breakpoint file="/Users/Dmitry/Unity/Z Project/Assets/_FreedomForZombie/Scripts/StateMachine/Transitions/ExitFromAreaTransition.cs" relfile="Assets/_FreedomForZombie/Scripts/StateMachine/Transitions/ExitFromAreaTransition.cs" line="20" column="1" />
      <Breakpoint file="/Users/Dmitry/Unity/Z Project/Assets/_FreedomForZombie/Scripts/DataService.cs" relfile="Assets/_FreedomForZombie/Scripts/DataService.cs" line="42" column="1" />
      <Breakpoint file="/Users/Dmitry/Unity/Z Project/Assets/_FreedomForZombie/Scripts/DataService.cs" relfile="Assets/_FreedomForZombie/Scripts/DataService.cs" line="47" column="1" />
      <Breakpoint file="/Users/Dmitry/Unity/Z Project/Assets/_FreedomForZombie/Scripts/DataService.cs" relfile="Assets/_FreedomForZombie/Scripts/DataService.cs" line="49" column="1" />
    </BreakpointStore>
  </MonoDevelop.Ide.DebuggingService.Breakpoints>
  <MultiItemStartupConfigurations />
</Properties>